falcon_error_handling/__init__.py
falcon_error_handling-0.0.6.dist-info/METADATA
falcon_error_handling-0.0.6.dist-info/WHEEL
falcon_error_handling-0.0.6.dist-info/top_level.txt
falcon_error_handling-0.0.6.dist-info/RECORD
